brainevent/__init__.py
brainevent/_compatible_import.py
brainevent/_config.py
brainevent/_error.py
brainevent/_jitc_matrix.py
brainevent/_misc.py
brainevent/_misc_test.py
brainevent/_pallas_random.py
brainevent/_primitives.py
brainevent/_primitives_test.py
brainevent/_test_util.py
brainevent/_typing.py
brainevent/_block_csr/__init__.py
brainevent/_block_csr/binary.py
brainevent/_block_csr/block_csr.py
brainevent/_block_csr/float.py
brainevent/_block_csr/test.py
brainevent/_block_ell/__init__.py
brainevent/_block_ell/binary.py
brainevent/_block_ell/block_ell.py
brainevent/_block_ell/float.py
brainevent/_coo/__init__.py
brainevent/_coo/binary.py
brainevent/_coo/binary_test.py
brainevent/_coo/float.py
brainevent/_coo/float_test.py
brainevent/_coo/main.py
brainevent/_coo/plasticity.py
brainevent/_coo/plasticity_test.py
brainevent/_coo/test_util.py
brainevent/_csr/__init__.py
brainevent/_csr/binary.py
brainevent/_csr/binary_test.py
brainevent/_csr/diag_add.py
brainevent/_csr/float.py
brainevent/_csr/float_test.py
brainevent/_csr/main.py
brainevent/_csr/main_test.py
brainevent/_csr/masked_float.py
brainevent/_csr/plasticity.py
brainevent/_csr/plasticity_test.py
brainevent/_csr/spsolve.py
brainevent/_csr/test_util.py
brainevent/_dense/__init__.py
brainevent/_dense/binary.py
brainevent/_dense/binary_index.py
brainevent/_dense/binary_test.py
brainevent/_dense/masked_float.py
brainevent/_dense/plasticity.py
brainevent/_dense/plasticity_test.py
brainevent/_event/__init__.py
brainevent/_event/base.py
brainevent/_event/base_test.py
brainevent/_event/binary.py
brainevent/_event/binary_index.py
brainevent/_event/binary_index_extraction.py
brainevent/_event/binary_test.py
brainevent/_event/masked_float.py
brainevent/_event/masked_float_index.py
brainevent/_event/masked_float_test.py
brainevent/_fixed_conn_num/__init__.py
brainevent/_fixed_conn_num/binary.py
brainevent/_fixed_conn_num/binary_test.py
brainevent/_fixed_conn_num/float.py
brainevent/_fixed_conn_num/float_test.py
brainevent-0.0.5.dist-info/licenses/LICENSE
brainevent-0.0.5.dist-info/METADATA
brainevent-0.0.5.dist-info/WHEEL
brainevent-0.0.5.dist-info/top_level.txt
brainevent-0.0.5.dist-info/RECORD
