Metadata-Version: 2.4
Name: brainevent
Version: 0.0.5
Summary: Event-driven Computation in JAX for Brain Dynamics.
Author-email: BrainEvent Developers <chao.brain@qq.com>
Project-URL: homepage, https://github.com/chaobrain/brainevent
Project-URL: repository, https://github.com/chaobrain/brainevent
Project-URL: Bug Tracker, https://github.com/chaobrain/brainevent/issues
Project-URL: Documentation, https://brainevent.readthedocs.io/
Project-URL: Source Code, https://github.com/chaobrain/brainevent
Keywords: computational neuroscience,brain-inspired computation,brain dynamics programming
Classifier: Natural Language :: English
Classifier: Operating System :: OS Independent
Classifier: Programming Language :: Python
Classifier: Programming Language :: Python :: 3
Classifier: Programming Language :: Python :: 3.10
Classifier: Programming Language :: Python :: 3.11
Classifier: Programming Language :: Python :: 3.12
Classifier: Programming Language :: Python :: 3.13
Classifier: Programming Language :: Python :: 3.14
Classifier: Intended Audience :: Science/Research
Classifier: Topic :: Scientific/Engineering :: Bio-Informatics
Classifier: Topic :: Scientific/Engineering :: Mathematics
Classifier: Topic :: Scientific/Engineering :: Artificial Intelligence
Classifier: Topic :: Software Development :: Libraries
Requires-Python: >=3.10
License-File: LICENSE
Requires-Dist: numpy>=1.15
Requires-Dist: brainunit>=0.0.8
Requires-Dist: absl-py
Provides-Extra: cpu
Requires-Dist: jax[cpu]; extra == "cpu"
Requires-Dist: numba; extra == "cpu"
Requires-Dist: brainunit; extra == "cpu"
Provides-Extra: cuda12
Requires-Dist: jax[cuda12]; extra == "cuda12"
Requires-Dist: warp-lang; extra == "cuda12"
Requires-Dist: brainunit; extra == "cuda12"
Provides-Extra: cuda13
Requires-Dist: jax[cuda13]; extra == "cuda13"
Requires-Dist: warp-lang; extra == "cuda13"
Requires-Dist: brainunit; extra == "cuda13"
Provides-Extra: tpu
Requires-Dist: jax[tpu]; extra == "tpu"
Requires-Dist: brainunit; extra == "tpu"
Provides-Extra: testing
Requires-Dist: pytest; extra == "testing"
Requires-Dist: jax; extra == "testing"
Requires-Dist: brainunit; extra == "testing"
Requires-Dist: absl-py; extra == "testing"
Dynamic: license-file
